{
  "_class": "shapeGroup",
  "clippingMaskMode": 0,
  "do_objectID": "CAF02BA1-7BDE-4625-9890-989A9C3F916A",
  "exportOptions": {
    "_class": "exportOptions",
    "exportFormats": [
    ],
    "includedLayerIds": [
    ],
    "layerOptions": 0,
    "shouldTrim": false
  },
  "frame": {
    "_class": "rect",
    "constrainProportions": false,
    "height": 16,
    "width": 320,
    "x": 0,
    "y": 1312
  },
  "hasClickThrough": false,
  "hasClippingMask": false,
  "isFlippedHorizontal": false,
  "isFlippedVertical": false,
  "isLocked": false,
  "isVisible": true,
  "layerListExpandedType": 0,
  "layers": [
    {
      "class": "rectangle",
      "id": "7B7D9C8F-9962-4E14-8DD0-24F595122D50"
    }
  ],
  "name": "Gutter",
  "nameIsFixed": true,
  "resizingConstraint": 63,
  "resizingType": 0,
  "rotation": 0,
  "shouldBreakMaskChain": false,
  "style": {
    "sharedObjectID": "0D0FD11D-B603-4FA9-A84D-ED052D9A141C"
  },
  "windingRule": 1
}