{
  "_class": "shapeGroup",
  "clippingMaskMode": 0,
  "do_objectID": "5F016056-D558-47AC-BC0B-9E1F2F87516F",
  "exportOptions": {
    "_class": "exportOptions",
    "exportFormats": [
    ],
    "includedLayerIds": [
    ],
    "layerOptions": 0,
    "shouldTrim": false
  },
  "frame": {
    "_class": "rect",
    "constrainProportions": false,
    "height": 8,
    "width": 320,
    "x": 0,
    "y": 384
  },
  "hasClickThrough": false,
  "hasClippingMask": false,
  "isFlippedHorizontal": false,
  "isFlippedVertical": false,
  "isLocked": false,
  "isVisible": true,
  "layerListExpandedType": 0,
  "layers": [
    {
      "class": "rectangle",
      "id": "17B6EBB6-BBBA-4770-8E9F-12B8B0FE4C81"
    }
  ],
  "name": "Gutter",
  "nameIsFixed": true,
  "resizingConstraint": 63,
  "resizingType": 0,
  "rotation": 0,
  "shouldBreakMaskChain": false,
  "style": {
    "sharedObjectID": "0D0FD11D-B603-4FA9-A84D-ED052D9A141C"
  },
  "windingRule": 1
}