{
  "_class": "shapeGroup",
  "clippingMaskMode": 0,
  "do_objectID": "2EE2F83C-5D42-47E4-8ABB-6BAF4222C06B",
  "exportOptions": {
    "_class": "exportOptions",
    "exportFormats": [
    ],
    "includedLayerIds": [
    ],
    "layerOptions": 0,
    "shouldTrim": false
  },
  "frame": {
    "_class": "rect",
    "constrainProportions": false,
    "height": 16,
    "width": 320,
    "x": 0,
    "y": 32
  },
  "hasClickThrough": false,
  "hasClippingMask": false,
  "isFlippedHorizontal": false,
  "isFlippedVertical": false,
  "isLocked": false,
  "isVisible": true,
  "layerListExpandedType": 0,
  "layers": [
    {
      "class": "rectangle",
      "id": "B2D0C33A-5E33-463B-8566-26A978D22619"
    }
  ],
  "name": "Gutter",
  "nameIsFixed": true,
  "resizingConstraint": 63,
  "resizingType": 0,
  "rotation": 0,
  "shouldBreakMaskChain": false,
  "style": {
    "sharedObjectID": "0D0FD11D-B603-4FA9-A84D-ED052D9A141C"
  },
  "windingRule": 1
}