{
  "_class": "shapeGroup",
  "clippingMaskMode": 0,
  "do_objectID": "47090C33-93CD-4FC4-8AF6-8C18B94F5FD3",
  "exportOptions": {
    "_class": "exportOptions",
    "exportFormats": [
    ],
    "includedLayerIds": [
    ],
    "layerOptions": 0,
    "shouldTrim": false
  },
  "frame": {
    "_class": "rect",
    "constrainProportions": false,
    "height": 8,
    "width": 320,
    "x": 0,
    "y": 64
  },
  "hasClickThrough": false,
  "hasClippingMask": false,
  "isFlippedHorizontal": false,
  "isFlippedVertical": false,
  "isLocked": false,
  "isVisible": true,
  "layerListExpandedType": 0,
  "layers": [
    {
      "class": "rectangle",
      "id": "676672D3-ABD2-4B7C-8CCE-DE58AE00C649"
    }
  ],
  "name": "Gutter",
  "nameIsFixed": true,
  "resizingConstraint": 63,
  "resizingType": 0,
  "rotation": 0,
  "shouldBreakMaskChain": false,
  "style": {
    "sharedObjectID": "0D0FD11D-B603-4FA9-A84D-ED052D9A141C"
  },
  "windingRule": 1
}