{
  "_class": "shapeGroup",
  "clippingMaskMode": 0,
  "do_objectID": "C58B0AAB-5D4C-44F3-9526-214848E2A04A",
  "exportOptions": {
    "_class": "exportOptions",
    "exportFormats": [
    ],
    "includedLayerIds": [
    ],
    "layerOptions": 0,
    "shouldTrim": false
  },
  "frame": {
    "_class": "rect",
    "constrainProportions": false,
    "height": 8,
    "width": 320,
    "x": 0,
    "y": 800
  },
  "hasClickThrough": false,
  "hasClippingMask": false,
  "isFlippedHorizontal": false,
  "isFlippedVertical": false,
  "isLocked": false,
  "isVisible": true,
  "layerListExpandedType": 0,
  "layers": [
    {
      "class": "rectangle",
      "id": "AE1A7132-707A-4A3D-8B6A-7310691DD3EF"
    }
  ],
  "name": "Gutter",
  "nameIsFixed": true,
  "resizingConstraint": 63,
  "resizingType": 0,
  "rotation": 0,
  "shouldBreakMaskChain": false,
  "style": {
    "sharedObjectID": "0D0FD11D-B603-4FA9-A84D-ED052D9A141C"
  },
  "windingRule": 1
}